Metadata-Version: 2.1
Name: odoo14-addon-delivery_price_collection_cost_product_domain
Version: 14.0.1.0.1
Summary: Bridge module between Delivery Collection Cost and Product Domain
Home-page: https://github.com/OCA/delivery-carrier
Author: PyTech SRL, Ooops, Odoo Community Association (OCA)
Author-email: support@odoo-community.org
License: AGPL-3
Classifier: Programming Language :: Python
Classifier: Framework :: Odoo
Classifier: Framework :: Odoo :: 14.0
Classifier: License :: OSI Approved :: GNU Affero General Public License v3
Requires-Python: >=3.6
Requires-Dist: odoo14-addon-delivery-price-collection-cost
Requires-Dist: odoo14-addon-delivery-price-product-domain
Requires-Dist: odoo<14.1dev,>=14.0a
